.coveragerc
.mailmap
.pylintrc
.testr.conf
AUTHORS
CONTRIBUTING.rst
ChangeLog
HACKING.rst
LICENSE
MANIFEST.in
README.rst
TESTING.rst
babel.cfg
openstack-common.conf
requirements.txt
run_tests.sh
setup.cfg
setup.py
test-requirements.txt
tox.ini
bin/neutron-rootwrap
bin/neutron-rootwrap-xen-dom0
doc/Makefile
doc/pom.xml
doc/source/conf.py
doc/source/index.rst
doc/source/devref/advanced_services.rst
doc/source/devref/api_extensions.rst
doc/source/devref/api_layer.rst
doc/source/devref/common.rst
doc/source/devref/db_layer.rst
doc/source/devref/development.environment.rst
doc/source/devref/fwaas.rst
doc/source/devref/index.rst
doc/source/devref/l2_agents.rst
doc/source/devref/layer3.rst
doc/source/devref/lbaas.rst
doc/source/devref/linuxbridge_agent.rst
doc/source/devref/openvswitch_agent.rst
doc/source/devref/plugin-api.rst
doc/source/devref/rpc_api.rst
doc/source/devref/security_group_api.rst
doc/source/devref/vpnaas.rst
doc/source/docbkx/docbkx-example/README
doc/source/docbkx/docbkx-example/pom.xml
doc/source/docbkx/docbkx-example/src/docbkx/example.xml
doc/source/docbkx/docbkx-example/src/docbkx/figures/example.sdx
doc/source/docbkx/docbkx-example/src/docbkx/figures/example.svg
doc/source/docbkx/quantum-api-1.0/common.ent
doc/source/docbkx/quantum-api-1.0/quantum-api-guide.xml
doc/source/docbkx/quantum-api-1.0/figures/Arrow_east.svg
doc/source/docbkx/quantum-api-1.0/figures/Check_mark_23x20_02.svg
doc/source/docbkx/quantum-api-1.0/js/shjs/sh_java.js
doc/source/docbkx/quantum-api-1.0/js/shjs/sh_javascript.js
doc/source/docbkx/quantum-api-1.0/js/shjs/sh_main.js
doc/source/docbkx/quantum-api-1.0/js/shjs/sh_xml.js
doc/source/docbkx/quantum-api-1.0/js/trc/util.js
doc/source/docbkx/quantum-api-1.0/js/trc/schema/controller.js
doc/source/docbkx/quantum-api-1.0/js/trc/schema/layoutManager.js
doc/source/docbkx/quantum-api-1.0/js/trc/schema/sampleManager.js
doc/source/docbkx/quantum-api-1.0/samples/att-get-res-none.json
gbptestneutron.egg-info/PKG-INFO
gbptestneutron.egg-info/SOURCES.txt
gbptestneutron.egg-info/dependency_links.txt
gbptestneutron.egg-info/entry_points.txt
gbptestneutron.egg-info/not-zip-safe
gbptestneutron.egg-info/requires.txt
gbptestneutron.egg-info/top_level.txt
